Workbook

Sheet Start Here
A1: Freelancer Finance & Business Toolkit
A2: A complete, automatic money dashboard for freelancers & solo businesses.
B5: HOW TO USE THIS TOOLKIT
B6: 1. Open the Settings tab and fill in your goal, currency and tax rate.
B7: 2. Log invoices on the Income tab. Mark each one Paid / Unpaid.
B8: 3. Log costs on the Expenses tab and pick a category.
B9: 4. Watch the Dashboard update itself — profit, tax to set aside, take-home.
B10: 5. Use the Rate Calculator to know exactly what to charge.
B11: 6. Track your pipeline on the Projects tab.
B13: WHAT'S INSIDE
B14: • Auto Dashboard with charts (income vs expenses, expenses by category)
B15: • Invoice tracker with Paid / Unpaid / Overdue status
B16: • Expense tracker with deductible flag for easy tax time
B17: • Tax set-aside estimator so you're never caught short
... B31: Thank you for your purchase! Questions? Reply to your order receipt.

Sheet Settings
A1: ⚙ Settings
A2: Set these once. Everything else updates automatically.
B4: SETTING | C4: VALUE | D4: NOTES
B5: Your name / business | C5: Your Name | D5: Shown for your own reference.
B6: Currency symbol | C6: € | D6: Type any symbol: €, $, £, etc.
B7: Annual income goal | C7: 30000 | D7: Used by the Rate Calculator.
B8: Billable hours per year | C8: 1200 | D8: Realistic billable hours (not total worked).
B9: Tax set-aside rate (%) | C9: 25 | D9: Rough % to reserve for income tax + social/self-employment.
B10: Business expenses / year (est.) | C10: 4000 | D10: Used by the Rate Calculator.
B13: Expense categories (edit freely): | D13: Invoice statuses:
B14: Software & subscriptions | D14: Paid
B15: Hardware & equipment | D15: Unpaid
B16: Office & supplies | D16: Overdue
B17: Travel & transport | D17: Draft
B18: Marketing & advertising
B19: Professional services
B20: Education & training | D20: Project statuses:
B21: Bank & payment fees | D21: Lead
B22: Insurance | D22: Proposal sent
B23: Rent & utilities | D23: Active
B24: Meals & entertainment | D24: On hold
B25: Other | D25: Completed
D26: Cancelled

Sheet Income
A1: 💶 Income & Invoices
A2: Log every invoice. 'Paid' rows feed your Dashboard automatically.
A4: Date | B4: Client | C4: Invoice # | D4: Description | E4: Amount | F4: Status | G4: Date paid

Sheet Expenses
A1: 🧾 Expenses
A2: Track costs by category. Deductible totals feed your tax estimate.
A4: Date | B4: Vendor | C4: Category | D4: Description | E4: Amount | F4: Deductible?

Sheet Projects
A1: 📁 Project Tracker
A2: Pipeline + delivery at a glance. Value = Quoted rate × Est. hours.
A4: Project | B4: Client | C4: Status | D4: Est. hours | E4: Hourly rate | F4: Quoted value | G4: Actual hours | H4: Effective rate
F5: =IF(AND($D5<>"",$E5<>""),$D5*$E5,"") | H5: =IF(AND($F5<>"",$G5>0),$F5/$G5,"")
F6: =IF(AND($D6<>"",$E6<>""),$D6*$E6,"") | H6: =IF(AND($F6<>"",$G6>0),$F6/$G6,"")
F7: =IF(AND($D7<>"",$E7<>""),$D7*$E7,"") | H7: =IF(AND($F7<>"",$G7>0),$F7/$G7,"")
F8: =IF(AND($D8<>"",$E8<>""),$D8*$E8,"") | H8: =IF(AND($F8<>"",$G8>0),$F8/$G8,"")
F9: =IF(AND($D9<>"",$E9<>""),$D9*$E9,"") | H9: =IF(AND($F9<>"",$G9>0),$F9/$G9,"")
F10: =IF(AND($D10<>"",$E10<>""),$D10*$E10,"") | H10: =IF(AND($F10<>"",$G10>0),$F10/$G10,"")
F11: =IF(AND($D11<>"",$E11<>""),$D11*$E11,"") | H11: =IF(AND($F11<>"",$G11>0),$F11/$G11,"")
F12: =IF(AND($D12<>"",$E12<>""),$D12*$E12,"") | H12: =IF(AND($F12<>"",$G12>0),$F12/$G12,"")
F13: =IF(AND($D13<>"",$E13<>""),$D13*$E13,"") | H13: =IF(AND($F13<>"",$G13>0),$F13/$G13,"")
F14: =IF(AND($D14<>"",$E14<>""),$D14*$E14,"") | H14: =IF(AND($F14<>"",$G14>0),$F14/$G14,"")
F15: =IF(AND($D15<>"",$E15<>""),$D15*$E15,"") | H15: =IF(AND($F15<>"",$G15>0),$F15/$G15,"")
F16: =IF(AND($D16<>"",$E16<>""),$D16*$E16,"") | H16: =IF(AND($F16<>"",$G16>0),$F16/$G16,"")
... F254: =IF(AND($D254<>"",$E254<>""),$D254*$E254,"") | H254: =IF(AND($F254<>"",$G254>0),$F254/$G254,"")

Sheet Rate Calculator
A1: 🧮 Rate Calculator
A2: What must you charge per hour to hit your goal? Edit Settings to change inputs.
B4: Your inputs come from the Settings tab.
B5: Annual income goal | C5: =Settings!$C$7
B6: Estimated annual expenses | C6: =Settings!$C$10
B7: Tax set-aside rate | C7: =Settings!$C$9/100
B8: Billable hours per year | C8: =Settings!$C$8
B10: Revenue needed (pre-tax) | C10: =(Settings!$C$7+Settings!$C$10)/(1-Settings!$C$9/100) | D10: Gross billings to net your goal after expenses & tax.
B11: → Required hourly rate | C11: =IF(Settings!$C$8>0,((Settings!$C$7+Settings!$C$10)/(1-Settings!$C$9/100))/Settings!$C$8,0) | D11: Charge at least this. Round up.
B12: → Required day rate (8h) | C12: =IF(Settings!$C$8>0,8*(((Settings!$C$7+Settings!$C$10)/(1-Settings!$C$9/100))/Settings!$C$8),0) | D12: A clean number for proposals.

Sheet Dashboard
A1: 📊 Dashboard
A2: Live snapshot of your business. Numbers update as you log income & expenses.
B4: Income received (Paid) | E4: Outstanding invoices
B5: =SUMIF(Income!$F$5:$F$254,"Paid",Income!$E$5:$E$254) | E5: =SUMIF(Income!$F$5:$F$254,"Unpaid",Income!$E$5:$E$254)+SUMIF(Income!$F$5:$F$254,"Overdue",Income!$E$5:$E$254)
B7: Total expenses | E7: Net profit
B8: =SUM(Expenses!$E$5:$E$254) | E8: =(SUMIF(Income!$F$5:$F$254,"Paid",Income!$E$5:$E$254)-SUM(Expenses!$E$5:$E$254))
B10: Estimated tax to set aside | E10: Estimated take-home
B11: =MAX(0,(SUMIF(Income!$F$5:$F$254,"Paid",Income!$E$5:$E$254)-SUMIF(Expenses!$F$5:$F$254,"Yes",Expenses!$E$5:$E$254)))*Settings!$C$9/100 | E11: =((SUMIF(Income!$F$5:$F$254,"Paid",Income!$E$5:$E$254)-SUM(Expenses!$E$5:$E$254))-(MAX(0,(SUMIF(Income!$F$5:$F$254,"Paid",Income!$E$5:$E$254)-SUMIF(Expenses!$F$5:$F$254,"Yes",Expenses!$E$5:$E$254)))*Settings!$C$9/100))
B14: Progress to annual income goal | C14: Goal
B15: =IF(Settings!$C$7>0,SUMIF(Income!$F$5:$F$254,"Paid",Income!$E$5:$E$254)/Settings!$C$7,0) | C15: =Settings!$C$7
E18: Month | F18: Income | G18: Expenses
E19: Jan | F19: =SUMPRODUCT((Income!$F$5:$F$254="Paid")*(MONTH(Income!$A$5:$A$254)=1)*(ISNUMBER(Income!$A$5:$A$254))*Income!$E$5:$E$254) | G19: =SUMPRODUCT((MONTH(Expenses!$A$5:$A$254)=1)*(ISNUMBER(Expenses!$A$5:$A$254))*Expenses!$E$5:$E$254)
E20: Feb | F20: =SUMPRODUCT((Income!$F$5:$F$254="Paid")*(MONTH(Income!$A$5:$A$254)=2)*(ISNUMBER(Income!$A$5:$A$254))*Income!$E$5:$E$254) | G20: =SUMPRODUCT((MONTH(Expenses!$A$5:$A$254)=2)*(ISNUMBER(Expenses!$A$5:$A$254))*Expenses!$E$5:$E$254)
E21: Mar | F21: =SUMPRODUCT((Income!$F$5:$F$254="Paid")*(MONTH(Income!$A$5:$A$254)=3)*(ISNUMBER(Income!$A$5:$A$254))*Income!$E$5:$E$254) | G21: =SUMPRODUCT((MONTH(Expenses!$A$5:$A$254)=3)*(ISNUMBER(Expenses!$A$5:$A$254))*Expenses!$E$5:$E$254)
E22: Apr | F22: =SUMPRODUCT((Income!$F$5:$F$254="Paid")*(MONTH(Income!$A$5:$A$254)=4)*(ISNUMBER(Income!$A$5:$A$254))*Income!$E$5:$E$254) | G22: =SUMPRODUCT((MONTH(Expenses!$A$5:$A$254)=4)*(ISNUMBER(Expenses!$A$5:$A$254))*Expenses!$E$5:$E$254)
E23: May | F23: =SUMPRODUCT((Income!$F$5:$F$254="Paid")*(MONTH(Income!$A$5:$A$254)=5)*(ISNUMBER(Income!$A$5:$A$254))*Income!$E$5:$E$254) | G23: =SUMPRODUCT((MONTH(Expenses!$A$5:$A$254)=5)*(ISNUMBER(Expenses!$A$5:$A$254))*Expenses!$E$5:$E$254)
E24: Jun | F24: =SUMPRODUCT((Income!$F$5:$F$254="Paid")*(MONTH(Income!$A$5:$A$254)=6)*(ISNUMBER(Income!$A$5:$A$254))*Income!$E$5:$E$254) | G24: =SUMPRODUCT((MONTH(Expenses!$A$5:$A$254)=6)*(ISNUMBER(Expenses!$A$5:$A$254))*Expenses!$E$5:$E$254)
E25: Jul | F25: =SUMPRODUCT((Income!$F$5:$F$254="Paid")*(MONTH(Income!$A$5:$A$254)=7)*(ISNUMBER(Income!$A$5:$A$254))*Income!$E$5:$E$254) | G25: =SUMPRODUCT((MONTH(Expenses!$A$5:$A$254)=7)*(ISNUMBER(Expenses!$A$5:$A$254))*Expenses!$E$5:$E$254)
E26: Aug | F26: =SUMPRODUCT((Income!$F$5:$F$254="Paid")*(MONTH(Income!$A$5:$A$254)=8)*(ISNUMBER(Income!$A$5:$A$254))*Income!$E$5:$E$254) | G26: =SUMPRODUCT((MONTH(Expenses!$A$5:$A$254)=8)*(ISNUMBER(Expenses!$A$5:$A$254))*Expenses!$E$5:$E$254)
E27: Sep | F27: =SUMPRODUCT((Income!$F$5:$F$254="Paid")*(MONTH(Income!$A$5:$A$254)=9)*(ISNUMBER(Income!$A$5:$A$254))*Income!$E$5:$E$254) | G27: =SUMPRODUCT((MONTH(Expenses!$A$5:$A$254)=9)*(ISNUMBER(Expenses!$A$5:$A$254))*Expenses!$E$5:$E$254)
E28: Oct | F28: =SUMPRODUCT((Income!$F$5:$F$254="Paid")*(MONTH(Income!$A$5:$A$254)=10)*(ISNUMBER(Income!$A$5:$A$254))*Income!$E$5:$E$254) | G28: =SUMPRODUCT((MONTH(Expenses!$A$5:$A$254)=10)*(ISNUMBER(Expenses!$A$5:$A$254))*Expenses!$E$5:$E$254)
E29: Nov | F29: =SUMPRODUCT((Income!$F$5:$F$254="Paid")*(MONTH(Income!$A$5:$A$254)=11)*(ISNUMBER(Income!$A$5:$A$254))*Income!$E$5:$E$254) | G29: =SUMPRODUCT((MONTH(Expenses!$A$5:$A$254)=11)*(ISNUMBER(Expenses!$A$5:$A$254))*Expenses!$E$5:$E$254)
E30: Dec | F30: =SUMPRODUCT((Income!$F$5:$F$254="Paid")*(MONTH(Income!$A$5:$A$254)=12)*(ISNUMBER(Income!$A$5:$A$254))*Income!$E$5:$E$254) | G30: =SUMPRODUCT((MONTH(Expenses!$A$5:$A$254)=12)*(ISNUMBER(Expenses!$A$5:$A$254))*Expenses!$E$5:$E$254)
E33: Category | F33: Spent
E34: Software & subscriptions | F34: =SUMIF(Expenses!$C$5:$C$254,$E34,Expenses!$E$5:$E$254)
E35: Hardware & equipment | F35: =SUMIF(Expenses!$C$5:$C$254,$E35,Expenses!$E$5:$E$254)
E36: Office & supplies | F36: =SUMIF(Expenses!$C$5:$C$254,$E36,Expenses!$E$5:$E$254)
E37: Travel & transport | F37: =SUMIF(Expenses!$C$5:$C$254,$E37,Expenses!$E$5:$E$254)
E38: Marketing & advertising | F38: =SUMIF(Expenses!$C$5:$C$254,$E38,Expenses!$E$5:$E$254)
E39: Professional services | F39: =SUMIF(Expenses!$C$5:$C$254,$E39,Expenses!$E$5:$E$254)
E40: Education & training | F40: =SUMIF(Expenses!$C$5:$C$254,$E40,Expenses!$E$5:$E$254)
E41: Bank & payment fees | F41: =SUMIF(Expenses!$C$5:$C$254,$E41,Expenses!$E$5:$E$254)
E42: Insurance | F42: =SUMIF(Expenses!$C$5:$C$254,$E42,Expenses!$E$5:$E$254)
E43: Rent & utilities | F43: =SUMIF(Expenses!$C$5:$C$254,$E43,Expenses!$E$5:$E$254)
E44: Meals & entertainment | F44: =SUMIF(Expenses!$C$5:$C$254,$E44,Expenses!$E$5:$E$254)
E45: Other | F45: =SUMIF(Expenses!$C$5:$C$254,$E45,Expenses!$E$5:$E$254)
